alumathgroup25/__init__.py
alumathgroup25/main.py
alumathgroup_twenty_five-1.0.0.dist-info/METADATA
alumathgroup_twenty_five-1.0.0.dist-info/WHEEL
alumathgroup_twenty_five-1.0.0.dist-info/top_level.txt
alumathgroup_twenty_five-1.0.0.dist-info/RECORD
