Metadata-Version: 2.4
Name: alumathgroup_twenty_five
Version: 1.0.0
Summary: A friendly matrix multiplication package by Kabango Mathias.
Author: Kabango Mathias, Orpheus Manga, Reine Mizero
Author-email: m.kabango@alustudent.com
Requires-Python: >=3.6
Dynamic: author
Dynamic: author-email
Dynamic: requires-python
Dynamic: summary
